invenio_celery/__init__.py
invenio_celery/config.py
invenio_celery/ext.py
invenio_celery-2.2.0.dist-info/licenses/AUTHORS.rst
invenio_celery-2.2.0.dist-info/licenses/LICENSE
invenio_celery-2.2.0.dist-info/METADATA
invenio_celery-2.2.0.dist-info/WHEEL
invenio_celery-2.2.0.dist-info/entry_points.txt
invenio_celery-2.2.0.dist-info/top_level.txt
invenio_celery-2.2.0.dist-info/RECORD
