Metadata-Version: 2.4
Name: invenio-celery
Version: 2.2.0
Summary: "Celery module for Invenio."
Home-page: https://github.com/inveniosoftware/invenio-celery
Author: CERN
Author-email: info@inveniosoftware.org
License: MIT
Keywords: invenio celery
Platform: any
Classifier: Development Status :: 5 - Production/Stable
Requires-Python: >=3.7
License-File: LICENSE
License-File: AUTHORS.rst
Requires-Dist: celery<5.5,>=5.1.0
Requires-Dist: Flask-CeleryExt>=0.3.4
Requires-Dist: invenio-base<3.0.0,>=2.3.0
Requires-Dist: msgpack>=0.6.2
Requires-Dist: redis>=2.10.0
Provides-Extra: tests
Requires-Dist: pytest-black-ng>=0.4.0; extra == "tests"
Requires-Dist: pytest-invenio<4.0.0,>=3.0.0; extra == "tests"
Requires-Dist: Sphinx<6.0.0,>=5.0.0; extra == "tests"
Provides-Extra: docs
Dynamic: license-file
